i3_quickterm/__init__.py
i3_quickterm/i3_quickterm.py
i3_quickterm/version.py
i3_qt-0.0.2.dist-info/LICENSE
i3_qt-0.0.2.dist-info/METADATA
i3_qt-0.0.2.dist-info/WHEEL
i3_qt-0.0.2.dist-info/entry_points.txt
i3_qt-0.0.2.dist-info/top_level.txt
i3_qt-0.0.2.dist-info/RECORD
