Metadata-Version: 2.2
Name: i3-qt
Version: 0.0.2
Summary: A small drop-down terminal for i3 and sway
Home-page: https://github.com/laur89/i3-quickterm
Author: laur89
License: MIT
Project-URL: Bug Reports, https://github.com/laur89/i3-quickterm/issues
Project-URL: Source, https://github.com/laur89/i3-quickterm
Keywords: i3 i3wm extensions add-ons
Classifier: Development Status :: 4 - Beta
Classifier: Intended Audience :: End Users/Desktop
Classifier: Topic :: Desktop Environment
Classifier: Topic :: Terminals :: Terminal Emulators/X Terminals
Classifier: License :: OSI Approved :: MIT License
Classifier: Programming Language :: Python :: 3
Classifier: Programming Language :: Python :: 3.8
Classifier: Programming Language :: Python :: 3.9
Classifier: Programming Language :: Python :: 3.10
Classifier: Programming Language :: Python :: 3.11
Classifier: Programming Language :: Python :: 3.12
Requires-Python: >=3.8
License-File: LICENSE
Requires-Dist: i3ipc>=2.0.1
Requires-Dist: tendo
Dynamic: author
Dynamic: classifier
Dynamic: description
Dynamic: description-content-type
Dynamic: home-page
Dynamic: keywords
Dynamic: license
Dynamic: project-url
Dynamic: requires-dist
Dynamic: requires-python
Dynamic: summary
